{
  "generatedAt": "2026-05-13T17:36:20.414Z",
  "flights": [
    {
      "id": "40812e",
      "callsign": "EZY34FE",
      "registration": "G-UZLZ",
      "aircraftType": "A20N",
      "originCountry": null,
      "lat": 34.5755,
      "lon": 30.8893,
      "altitudeFeet": 37500,
      "speedKnots": 443,
      "heading": 353,
      "verticalRateMps": 0,
      "onGround": false,
      "squawk": "5435",
      "lastContactAgeSec": 0,
      "timePositionAgeSec": 1
    },
    {
      "id": "4d22ac",
      "callsign": "BBG252",
      "registration": "9H-HLY",
      "aircraftType": "B738",
      "originCountry": null,
      "lat": 33.381,
      "lon": 30.9411,
      "altitudeFeet": 39650,
      "speedKnots": 379,
      "heading": 294,
      "verticalRateMps": 64,
      "onGround": false,
      "squawk": "5657",
      "lastContactAgeSec": 0,
      "timePositionAgeSec": 0
    },
    {
      "id": "4bb062",
      "callsign": "THY8HG",
      "registration": "TC-LCB",
      "aircraftType": "B38M",
      "originCountry": null,
      "lat": 31.5884,
      "lon": 31.1592,
      "altitudeFeet": 36775,
      "speedKnots": 465,
      "heading": 167,
      "verticalRateMps": 0,
      "onGround": false,
      "squawk": "1626",
      "lastContactAgeSec": 0,
      "timePositionAgeSec": 5
    },
    {
      "id": "010108",
      "callsign": "MSR712",
      "registration": "SU-GCZ",
      "aircraftType": "B738",
      "originCountry": null,
      "lat": 32.1241,
      "lon": 31.2207,
      "altitudeFeet": 32600,
      "speedKnots": 434,
      "heading": 235,
      "verticalRateMps": 32,
      "onGround": false,
      "squawk": "1676",
      "lastContactAgeSec": 0,
      "timePositionAgeSec": 0
    },
    {
      "id": "4bb073",
      "callsign": "THY31M",
      "registration": "TC-LCS",
      "aircraftType": "B38M",
      "originCountry": null,
      "lat": 31.0394,
      "lon": 31.2861,
      "altitudeFeet": 36850,
      "speedKnots": 459,
      "heading": 167,
      "verticalRateMps": 32,
      "onGround": false,
      "squawk": "1606",
      "lastContactAgeSec": 0,
      "timePositionAgeSec": 0
    },
    {
      "id": "46da6c",
      "callsign": "SEH3LC",
      "registration": "SX-VSL",
      "aircraftType": "A320",
      "originCountry": null,
      "lat": 35.5029,
      "lon": 31.312,
      "altitudeFeet": 37575,
      "speedKnots": 530,
      "heading": 107,
      "verticalRateMps": -832,
      "onGround": false,
      "squawk": "7413",
      "lastContactAgeSec": 0,
      "timePositionAgeSec": 0
    },
    {
      "id": "738063",
      "callsign": "ELY2367",
      "registration": "4X-EKA",
      "aircraftType": "B738",
      "originCountry": null,
      "lat": 33.6839,
      "lon": 31.4712,
      "altitudeFeet": 37600,
      "speedKnots": 390,
      "heading": 303,
      "verticalRateMps": 0,
      "onGround": false,
      "squawk": "4151",
      "lastContactAgeSec": 0,
      "timePositionAgeSec": 0
    },
    {
      "id": "40773b",
      "callsign": "TOM9CD",
      "registration": "G-TUMK",
      "aircraftType": "B38M",
      "originCountry": null,
      "lat": 35.62,
      "lon": 31.761,
      "altitudeFeet": 30750,
      "speedKnots": 508,
      "heading": 119,
      "verticalRateMps": -1920,
      "onGround": false,
      "squawk": "2222",
      "lastContactAgeSec": 0,
      "timePositionAgeSec": 0
    },
    {
      "id": "7448a6",
      "callsign": "RJA138",
      "registration": "JY-REF",
      "aircraftType": "E295",
      "originCountry": null,
      "lat": 34.8818,
      "lon": 31.9508,
      "altitudeFeet": 38450,
      "speedKnots": 475,
      "heading": 142,
      "verticalRateMps": 0,
      "onGround": false,
      "squawk": "7606",
      "lastContactAgeSec": 0,
      "timePositionAgeSec": 0
    },
    {
      "id": "4070ed",
      "callsign": "EXS84FN",
      "registration": "G-JZHZ",
      "aircraftType": "B738",
      "originCountry": null,
      "lat": 35.2232,
      "lon": 32.3709,
      "altitudeFeet": 21450,
      "speedKnots": 414,
      "heading": 108,
      "verticalRateMps": -1504,
      "onGround": false,
      "squawk": "1157",
      "lastContactAgeSec": 0,
      "timePositionAgeSec": 0
    },
    {
      "id": "aab841",
      "callsign": "CKS703",
      "registration": "N790CK",
      "aircraftType": "B77W",
      "originCountry": null,
      "lat": 33.085,
      "lon": 32.4673,
      "altitudeFeet": 39700,
      "speedKnots": 432,
      "heading": 336,
      "verticalRateMps": -32,
      "onGround": false,
      "squawk": "1333",
      "lastContactAgeSec": 0,
      "timePositionAgeSec": 0
    },
    {
      "id": "896315",
      "callsign": "UAE192",
      "registration": "A6-ENS",
      "aircraftType": "B77W",
      "originCountry": null,
      "lat": 34.7433,
      "lon": 32.5738,
      "altitudeFeet": 38500,
      "speedKnots": 548,
      "heading": 97,
      "verticalRateMps": 0,
      "onGround": false,
      "squawk": "2245",
      "lastContactAgeSec": 0,
      "timePositionAgeSec": 0
    },
    {
      "id": "4066d0",
      "callsign": "TOM5TN",
      "registration": "G-TAWI",
      "aircraftType": "B738",
      "originCountry": null,
      "lat": 34.6758,
      "lon": 32.6236,
      "altitudeFeet": 2250,
      "speedKnots": 155,
      "heading": 290,
      "verticalRateMps": 0,
      "onGround": false,
      "squawk": "2151",
      "lastContactAgeSec": 0,
      "timePositionAgeSec": 0
    },
    {
      "id": "80158c",
      "callsign": "AIC112",
      "registration": "VT-TSP",
      "aircraftType": "B789",
      "originCountry": null,
      "lat": 31.9175,
      "lon": 32.6866,
      "altitudeFeet": 40825,
      "speedKnots": 518,
      "heading": 144,
      "verticalRateMps": 0,
      "onGround": false,
      "squawk": "2243",
      "lastContactAgeSec": 0,
      "timePositionAgeSec": 2
    },
    {
      "id": "744829",
      "callsign": "RJA126",
      "registration": "JY-RAI",
      "aircraftType": "A20N",
      "originCountry": null,
      "lat": 33.7092,
      "lon": 32.9782,
      "altitudeFeet": 36600,
      "speedKnots": 486,
      "heading": 148,
      "verticalRateMps": -32,
      "onGround": false,
      "squawk": "7656",
      "lastContactAgeSec": 0,
      "timePositionAgeSec": 0
    },
    {
      "id": "89647a",
      "callsign": "UAE98P",
      "registration": "A6-EUP",
      "aircraftType": "A388",
      "originCountry": null,
      "lat": 36.5041,
      "lon": 33.0937,
      "altitudeFeet": 42250,
      "speedKnots": 531,
      "heading": 128,
      "verticalRateMps": 0,
      "onGround": false,
      "squawk": "7537",
      "lastContactAgeSec": 0,
      "timePositionAgeSec": 0
    },
    {
      "id": "744822",
      "callsign": "RJA148",
      "registration": "JY-RAB",
      "aircraftType": "A20N",
      "originCountry": null,
      "lat": 33.3633,
      "lon": 33.2334,
      "altitudeFeet": 34675,
      "speedKnots": 501,
      "heading": 148,
      "verticalRateMps": -704,
      "onGround": false,
      "squawk": "7615",
      "lastContactAgeSec": 0,
      "timePositionAgeSec": 0
    },
    {
      "id": "4bb86e",
      "callsign": "PGT1984",
      "registration": "TC-NCN",
      "aircraftType": "A20N",
      "originCountry": null,
      "lat": 35.6751,
      "lon": 33.3324,
      "altitudeFeet": 13425,
      "speedKnots": 363,
      "heading": 141,
      "verticalRateMps": -1856,
      "onGround": false,
      "squawk": "2364",
      "lastContactAgeSec": 0,
      "timePositionAgeSec": 0
    },
    {
      "id": "06a0eb",
      "callsign": "QTR88R",
      "registration": "A7-AML",
      "aircraftType": "A359",
      "originCountry": null,
      "lat": 36.2425,
      "lon": 33.5067,
      "altitudeFeet": 40275,
      "speedKnots": 548,
      "heading": 128,
      "verticalRateMps": -64,
      "onGround": false,
      "squawk": "7233",
      "lastContactAgeSec": 0,
      "timePositionAgeSec": 0
    },
    {
      "id": "739602",
      "callsign": "HFA814",
      "registration": "4X-IHC",
      "aircraftType": "AT76",
      "originCountry": null,
      "lat": 34.7553,
      "lon": 33.6216,
      "altitudeFeet": 4475,
      "speedKnots": 183,
      "heading": 147,
      "verticalRateMps": 1312,
      "onGround": false,
      "squawk": "5272",
      "lastContactAgeSec": 0,
      "timePositionAgeSec": 0
    },
    {
      "id": "a95442",
      "callsign": "N70X",
      "registration": "N70X",
      "aircraftType": "CL60",
      "originCountry": null,
      "lat": 33.5274,
      "lon": 33.8768,
      "altitudeFeet": 23950,
      "speedKnots": 467,
      "heading": 176,
      "verticalRateMps": 64,
      "onGround": false,
      "squawk": "4147",
      "lastContactAgeSec": 0,
      "timePositionAgeSec": 1
    },
    {
      "id": "4c8096",
      "callsign": "CYP12L",
      "registration": "5B-DEA",
      "aircraftType": "BCS3",
      "originCountry": null,
      "lat": 34.6998,
      "lon": 33.8953,
      "altitudeFeet": 12375,
      "speedKnots": 333,
      "heading": 117,
      "verticalRateMps": 2432,
      "onGround": false,
      "squawk": "7347",
      "lastContactAgeSec": 0,
      "timePositionAgeSec": 0
    },
    {
      "id": "49d034",
      "callsign": "ISR873",
      "registration": "OK-TSR",
      "aircraftType": "B738",
      "originCountry": null,
      "lat": 35.1904,
      "lon": 34.0391,
      "altitudeFeet": 37400,
      "speedKnots": 416,
      "heading": 358,
      "verticalRateMps": -32,
      "onGround": false,
      "squawk": "4152",
      "lastContactAgeSec": 0,
      "timePositionAgeSec": 0
    },
    {
      "id": "155c63",
      "callsign": "RWZ4312",
      "registration": "RA-89187",
      "aircraftType": "SU95",
      "originCountry": null,
      "lat": 32.1512,
      "lon": 34.0751,
      "altitudeFeet": 22500,
      "speedKnots": 321,
      "heading": 284,
      "verticalRateMps": 2240,
      "onGround": false,
      "squawk": "6045",
      "lastContactAgeSec": 0,
      "timePositionAgeSec": 0
    },
    {
      "id": "7380c2",
      "callsign": "ELY091",
      "registration": "4X-EDC",
      "aircraftType": "B789",
      "originCountry": null,
      "lat": 34.8281,
      "lon": 34.1253,
      "altitudeFeet": 32750,
      "speedKnots": 469,
      "heading": 355,
      "verticalRateMps": 896,
      "onGround": false,
      "squawk": "4154",
      "lastContactAgeSec": 0,
      "timePositionAgeSec": 0
    },
    {
      "id": "50012b",
      "callsign": "T7VIP",
      "registration": "T7-VIP",
      "aircraftType": "CL60",
      "originCountry": null,
      "lat": 35.2152,
      "lon": 34.1428,
      "altitudeFeet": 27000,
      "speedKnots": 350,
      "heading": 3,
      "verticalRateMps": 1216,
      "onGround": false,
      "squawk": "6043",
      "lastContactAgeSec": 0,
      "timePositionAgeSec": 0
    },
    {
      "id": "4d203d",
      "callsign": "CHZ2255",
      "registration": "9H-CAH",
      "aircraftType": "B763",
      "originCountry": null,
      "lat": 33.212,
      "lon": 34.1519,
      "altitudeFeet": 25025,
      "speedKnots": 424,
      "heading": 355,
      "verticalRateMps": 0,
      "onGround": false,
      "squawk": "4130",
      "lastContactAgeSec": 0,
      "timePositionAgeSec": 0
    },
    {
      "id": "89617a",
      "callsign": "UAE1CL",
      "registration": "A6-EGB",
      "aircraftType": "B77W",
      "originCountry": null,
      "lat": 35.6951,
      "lon": 34.1781,
      "altitudeFeet": 38350,
      "speedKnots": 534,
      "heading": 149,
      "verticalRateMps": 32,
      "onGround": false,
      "squawk": "2713",
      "lastContactAgeSec": 0,
      "timePositionAgeSec": 0
    },
    {
      "id": "06a2e7",
      "callsign": "QTR44R",
      "registration": "A7-BHD",
      "aircraftType": "B789",
      "originCountry": null,
      "lat": 35.8397,
      "lon": 34.1995,
      "altitudeFeet": 40325,
      "speedKnots": 562,
      "heading": 117,
      "verticalRateMps": 0,
      "onGround": false,
      "squawk": "7631",
      "lastContactAgeSec": 0,
      "timePositionAgeSec": 0
    },
    {
      "id": "89639e",
      "callsign": "UAE6AL",
      "registration": "A6-EOE",
      "aircraftType": "A388",
      "originCountry": null,
      "lat": 35.6529,
      "lon": 34.2082,
      "altitudeFeet": 42275,
      "speedKnots": 517,
      "heading": 150,
      "verticalRateMps": 0,
      "onGround": false,
      "squawk": "5654",
      "lastContactAgeSec": 0,
      "timePositionAgeSec": 0
    },
    {
      "id": "744826",
      "callsign": "RJA124",
      "registration": "JY-RAF",
      "aircraftType": "A20N",
      "originCountry": null,
      "lat": 32.2832,
      "lon": 34.2947,
      "altitudeFeet": 19000,
      "speedKnots": 426,
      "heading": 117,
      "verticalRateMps": -1664,
      "onGround": false,
      "squawk": "6524",
      "lastContactAgeSec": 0,
      "timePositionAgeSec": 0
    },
    {
      "id": "896216",
      "callsign": "UAE73J",
      "registration": "A6-EGU",
      "aircraftType": "B77W",
      "originCountry": null,
      "lat": 35.389,
      "lon": 34.4012,
      "altitudeFeet": 36350,
      "speedKnots": 529,
      "heading": 149,
      "verticalRateMps": -32,
      "onGround": false,
      "squawk": "2703",
      "lastContactAgeSec": 0,
      "timePositionAgeSec": 0
    },
    {
      "id": "89671b",
      "callsign": "ETD1NV",
      "registration": "A6-EIJ",
      "aircraftType": "A320",
      "originCountry": null,
      "lat": 29.482,
      "lon": 34.4887,
      "altitudeFeet": 36950,
      "speedKnots": 482,
      "heading": 99,
      "verticalRateMps": 0,
      "onGround": false,
      "squawk": "7320",
      "lastContactAgeSec": 0,
      "timePositionAgeSec": 0
    },
    {
      "id": "06a109",
      "callsign": "QTR5G",
      "registration": "A7-ALU",
      "aircraftType": "A359",
      "originCountry": null,
      "lat": 35.5138,
      "lon": 34.9744,
      "altitudeFeet": 40300,
      "speedKnots": 552,
      "heading": 118,
      "verticalRateMps": 0,
      "onGround": false,
      "squawk": "7706",
      "lastContactAgeSec": 0,
      "timePositionAgeSec": 0
    },
    {
      "id": "896316",
      "callsign": "UAE1X",
      "registration": "A6-ENT",
      "aircraftType": "B77W",
      "originCountry": null,
      "lat": 34.9934,
      "lon": 35.1539,
      "altitudeFeet": 38425,
      "speedKnots": 551,
      "heading": 135,
      "verticalRateMps": -64,
      "onGround": false,
      "squawk": "4632",
      "lastContactAgeSec": 0,
      "timePositionAgeSec": 1
    },
    {
      "id": "8962e6",
      "callsign": "ETD7QB",
      "registration": "A6-ETH",
      "aircraftType": "B77W",
      "originCountry": null,
      "lat": 31.9359,
      "lon": 35.4425,
      "altitudeFeet": 9500,
      "speedKnots": 383,
      "heading": 92,
      "verticalRateMps": 64,
      "onGround": false,
      "squawk": "0752",
      "lastContactAgeSec": 0,
      "timePositionAgeSec": 0
    },
    {
      "id": "018032",
      "callsign": "5ADRK",
      "registration": "5A-DRK",
      "aircraftType": "C56X",
      "originCountry": null,
      "lat": 31.6061,
      "lon": 35.8658,
      "altitudeFeet": 15625,
      "speedKnots": 334,
      "heading": 184,
      "verticalRateMps": 1792,
      "onGround": false,
      "squawk": "0753",
      "lastContactAgeSec": 0,
      "timePositionAgeSec": 0
    },
    {
      "id": "8965cf",
      "callsign": "FDB143",
      "registration": "A6-FKD",
      "aircraftType": "B38M",
      "originCountry": null,
      "lat": 31.571,
      "lon": 36.5808,
      "altitudeFeet": 23125,
      "speedKnots": 280,
      "heading": 259,
      "verticalRateMps": -32,
      "onGround": false,
      "squawk": "6224",
      "lastContactAgeSec": 0,
      "timePositionAgeSec": 1
    },
    {
      "id": "010290",
      "callsign": "NMA426",
      "registration": "SU-NMN",
      "aircraftType": "A321",
      "originCountry": null,
      "lat": 36.6716,
      "lon": 37.3903,
      "altitudeFeet": 35250,
      "speedKnots": 420,
      "heading": 14,
      "verticalRateMps": 416,
      "onGround": false,
      "squawk": "6123",
      "lastContactAgeSec": 0,
      "timePositionAgeSec": 0
    },
    {
      "id": "06a09a",
      "callsign": "QTR39B",
      "registration": "A7-AHS",
      "aircraftType": "A320",
      "originCountry": null,
      "lat": 22.5401,
      "lon": 54.0704,
      "altitudeFeet": 29850,
      "speedKnots": 23,
      "heading": 140,
      "verticalRateMps": 32,
      "onGround": false,
      "squawk": "2153",
      "lastContactAgeSec": 0,
      "timePositionAgeSec": 12
    },
    {
      "id": "89662b",
      "callsign": "ETD432",
      "registration": "A6-ETA",
      "aircraftType": "B77W",
      "originCountry": null,
      "lat": 24.5058,
      "lon": 54.581,
      "altitudeFeet": 2775,
      "speedKnots": 219,
      "heading": 21,
      "verticalRateMps": 1088,
      "onGround": false,
      "squawk": "3412",
      "lastContactAgeSec": 0,
      "timePositionAgeSec": 0
    },
    {
      "id": "8016cb",
      "callsign": "AXB347",
      "registration": "VT-BWN",
      "aircraftType": "B38M",
      "originCountry": null,
      "lat": 24.4062,
      "lon": 54.7213,
      "altitudeFeet": 1150,
      "speedKnots": 147,
      "heading": 308,
      "verticalRateMps": -704,
      "onGround": false,
      "squawk": "4751",
      "lastContactAgeSec": 0,
      "timePositionAgeSec": 0
    },
    {
      "id": "896388",
      "callsign": "ETD1X7",
      "registration": "A6-EIU",
      "aircraftType": "A320",
      "originCountry": null,
      "lat": 24.238,
      "lon": 55.2241,
      "altitudeFeet": 14975,
      "speedKnots": 383,
      "heading": 119,
      "verticalRateMps": 2720,
      "onGround": false,
      "squawk": "3413",
      "lastContactAgeSec": 0,
      "timePositionAgeSec": 0
    },
    {
      "id": "4247b0",
      "callsign": "VPCZC",
      "registration": "VP-CZC",
      "aircraftType": "GLF6",
      "originCountry": null,
      "lat": 23.1231,
      "lon": 55.2735,
      "altitudeFeet": 33775,
      "speedKnots": 529,
      "heading": 24,
      "verticalRateMps": -2464,
      "onGround": false,
      "squawk": "1644",
      "lastContactAgeSec": 0,
      "timePositionAgeSec": 11
    },
    {
      "id": "8966d3",
      "callsign": "ETD9R5",
      "registration": "A6-XWJ",
      "aircraftType": "A35K",
      "originCountry": null,
      "lat": 24.0993,
      "lon": 55.5489,
      "altitudeFeet": 16075,
      "speedKnots": 429,
      "heading": 113,
      "verticalRateMps": 1856,
      "onGround": false,
      "squawk": "3427",
      "lastContactAgeSec": 0,
      "timePositionAgeSec": 1
    },
    {
      "id": "801832",
      "callsign": "AKJ589",
      "registration": null,
      "aircraftType": null,
      "originCountry": null,
      "lat": 23.9924,
      "lon": 55.7939,
      "altitudeFeet": 22400,
      "speedKnots": 436,
      "heading": 117,
      "verticalRateMps": 1344,
      "onGround": false,
      "squawk": "3450",
      "lastContactAgeSec": 0,
      "timePositionAgeSec": 44
    },
    {
      "id": "010207",
      "callsign": "MSR732",
      "registration": "SU-GFM",
      "aircraftType": "A20N",
      "originCountry": null,
      "lat": 31.8123,
      "lon": 30.8237,
      "altitudeFeet": 36975,
      "speedKnots": 494,
      "heading": 138,
      "verticalRateMps": -736,
      "onGround": false,
      "squawk": "1634",
      "lastContactAgeSec": 1,
      "timePositionAgeSec": 1
    },
    {
      "id": "896618",
      "callsign": "UAE9905",
      "registration": "A6-EFZ",
      "aircraftType": "B77L",
      "originCountry": null,
      "lat": 29.6093,
      "lon": 34.3097,
      "altitudeFeet": 34900,
      "speedKnots": 532,
      "heading": 101,
      "verticalRateMps": 32,
      "onGround": false,
      "squawk": "3333",
      "lastContactAgeSec": 1,
      "timePositionAgeSec": 3
    },
    {
      "id": "896627",
      "callsign": "UAE34Q",
      "registration": "A6-EXJ",
      "aircraftType": "A359",
      "originCountry": null,
      "lat": 34.1239,
      "lon": 37.2545,
      "altitudeFeet": 42400,
      "speedKnots": 547,
      "heading": 128,
      "verticalRateMps": 0,
      "onGround": false,
      "squawk": "4642",
      "lastContactAgeSec": 1,
      "timePositionAgeSec": 5
    },
    {
      "id": "710d9c",
      "callsign": "KNE8097",
      "registration": "HZ-NS37",
      "aircraftType": "A20N",
      "originCountry": null,
      "lat": 22.5565,
      "lon": 55.6539,
      "altitudeFeet": 37175,
      "speedKnots": 504,
      "heading": 68,
      "verticalRateMps": 0,
      "onGround": false,
      "squawk": "4237",
      "lastContactAgeSec": 1,
      "timePositionAgeSec": 9
    },
    {
      "id": "06a0b3",
      "callsign": "QTR401",
      "registration": "A7-BCO",
      "aircraftType": "B788",
      "originCountry": null,
      "lat": 31.4376,
      "lon": 36.3055,
      "altitudeFeet": 17125,
      "speedKnots": 414,
      "heading": 122,
      "verticalRateMps": 2368,
      "onGround": false,
      "squawk": "0704",
      "lastContactAgeSec": 2,
      "timePositionAgeSec": 10
    },
    {
      "id": "515309",
      "callsign": "SMR6415",
      "registration": "EY-777",
      "aircraftType": "B738",
      "originCountry": null,
      "lat": 24.3688,
      "lon": 61.1825,
      "altitudeFeet": 38100,
      "speedKnots": 406,
      "heading": 257,
      "verticalRateMps": 0,
      "onGround": false,
      "squawk": null,
      "lastContactAgeSec": 2,
      "timePositionAgeSec": 2
    },
    {
      "id": "7000a1",
      "callsign": "AFG401",
      "registration": "YA-FGF",
      "aircraftType": "A310",
      "originCountry": null,
      "lat": 24.2223,
      "lon": 60.2794,
      "altitudeFeet": 38100,
      "speedKnots": 421,
      "heading": 266,
      "verticalRateMps": -128,
      "onGround": false,
      "squawk": null,
      "lastContactAgeSec": 3,
      "timePositionAgeSec": 48
    },
    {
      "id": "761488",
      "callsign": "ABQ284",
      "registration": "AP-EDH",
      "aircraftType": "A320",
      "originCountry": null,
      "lat": 24.0819,
      "lon": 60.3623,
      "altitudeFeet": 36025,
      "speedKnots": 406,
      "heading": 250,
      "verticalRateMps": -32,
      "onGround": false,
      "squawk": null,
      "lastContactAgeSec": 3,
      "timePositionAgeSec": 10
    },
    {
      "id": "8966f0",
      "callsign": "UAE9642",
      "registration": "A6-EWN",
      "aircraftType": "B77L",
      "originCountry": null,
      "lat": 29.4363,
      "lon": 34.8957,
      "altitudeFeet": 36850,
      "speedKnots": 531,
      "heading": 101,
      "verticalRateMps": 0,
      "onGround": false,
      "squawk": "3362",
      "lastContactAgeSec": 4,
      "timePositionAgeSec": 37
    },
    {
      "id": "8963f7",
      "callsign": "UAE6FJ",
      "registration": "A6-EOZ",
      "aircraftType": "A388",
      "originCountry": null,
      "lat": 22.8981,
      "lon": 54.5801,
      "altitudeFeet": 39000,
      "speedKnots": 523,
      "heading": 78,
      "verticalRateMps": 0,
      "onGround": false,
      "squawk": "6014",
      "lastContactAgeSec": 4,
      "timePositionAgeSec": 7
    }
  ],
  "status": "adsb.lol ok (56)"
}
