{
  "generatedAt": "2026-07-01T06:41:34.371Z",
  "flights": [
    {
      "id": "01024b",
      "callsign": "MSC388",
      "registration": "SU-BUX",
      "aircraftType": "A20N",
      "originCountry": null,
      "lat": 33.5621,
      "lon": 30.6894,
      "altitudeFeet": 39600,
      "speedKnots": 435,
      "heading": 155,
      "verticalRateMps": 32,
      "onGround": false,
      "squawk": "5637",
      "lastContactAgeSec": 0,
      "timePositionAgeSec": 1
    },
    {
      "id": "504e89",
      "callsign": "FIA6343",
      "registration": "ER-00005",
      "aircraftType": "A320",
      "originCountry": null,
      "lat": 32.7152,
      "lon": 30.993,
      "altitudeFeet": 39625,
      "speedKnots": 424,
      "heading": 175,
      "verticalRateMps": 0,
      "onGround": false,
      "squawk": "5420",
      "lastContactAgeSec": 0,
      "timePositionAgeSec": 1
    },
    {
      "id": "151dc7",
      "callsign": "AFL734",
      "registration": "RA-73159",
      "aircraftType": "A333",
      "originCountry": null,
      "lat": 32.1037,
      "lon": 31.0605,
      "altitudeFeet": 39725,
      "speedKnots": 429,
      "heading": 175,
      "verticalRateMps": 0,
      "onGround": false,
      "squawk": "3331",
      "lastContactAgeSec": 0,
      "timePositionAgeSec": 0
    },
    {
      "id": "49d3d3",
      "callsign": "TVL5217",
      "registration": "OK-SWC",
      "aircraftType": "B38M",
      "originCountry": null,
      "lat": 32.9128,
      "lon": 31.0604,
      "altitudeFeet": 38575,
      "speedKnots": 488,
      "heading": 334,
      "verticalRateMps": 0,
      "onGround": false,
      "squawk": "6712",
      "lastContactAgeSec": 0,
      "timePositionAgeSec": 0
    },
    {
      "id": "4bb064",
      "callsign": "THY84W",
      "registration": "TC-LCD",
      "aircraftType": "B38M",
      "originCountry": null,
      "lat": 32.0673,
      "lon": 31.3113,
      "altitudeFeet": 40750,
      "speedKnots": 486,
      "heading": 355,
      "verticalRateMps": -32,
      "onGround": false,
      "squawk": "1673",
      "lastContactAgeSec": 0,
      "timePositionAgeSec": 0
    },
    {
      "id": "8964d0",
      "callsign": "FDB3UM",
      "registration": "A6-FMA",
      "aircraftType": "B38M",
      "originCountry": null,
      "lat": 31.8463,
      "lon": 31.3677,
      "altitudeFeet": 38625,
      "speedKnots": 471,
      "heading": 317,
      "verticalRateMps": 0,
      "onGround": false,
      "squawk": "0537",
      "lastContactAgeSec": 0,
      "timePositionAgeSec": 1
    },
    {
      "id": "4a0481",
      "callsign": "ISR730",
      "registration": "YR-ADA",
      "aircraftType": "A320",
      "originCountry": null,
      "lat": 35.3148,
      "lon": 31.4987,
      "altitudeFeet": 39525,
      "speedKnots": 455,
      "heading": 144,
      "verticalRateMps": 0,
      "onGround": false,
      "squawk": "5462",
      "lastContactAgeSec": 0,
      "timePositionAgeSec": 0
    },
    {
      "id": "4ba90c",
      "callsign": "THY8RZ",
      "registration": "TC-JHL",
      "aircraftType": "B738",
      "originCountry": null,
      "lat": 30.6052,
      "lon": 31.8804,
      "altitudeFeet": 39775,
      "speedKnots": 454,
      "heading": 145,
      "verticalRateMps": 0,
      "onGround": false,
      "squawk": "3323",
      "lastContactAgeSec": 0,
      "timePositionAgeSec": 0
    },
    {
      "id": "738284",
      "callsign": "ISR173",
      "registration": "4X-ABF",
      "aircraftType": "A320",
      "originCountry": null,
      "lat": 33.0894,
      "lon": 32.1272,
      "altitudeFeet": 32875,
      "speedKnots": 460,
      "heading": 302,
      "verticalRateMps": 704,
      "onGround": false,
      "squawk": "5567",
      "lastContactAgeSec": 0,
      "timePositionAgeSec": 0
    },
    {
      "id": "503cb4",
      "callsign": "KLJ5607",
      "registration": "YL-BBN",
      "aircraftType": "B738",
      "originCountry": null,
      "lat": 33.6219,
      "lon": 32.2351,
      "altitudeFeet": 42775,
      "speedKnots": 423,
      "heading": 317,
      "verticalRateMps": 32,
      "onGround": false,
      "squawk": "4130",
      "lastContactAgeSec": 0,
      "timePositionAgeSec": 0
    },
    {
      "id": "4d248f",
      "callsign": "WZZ993",
      "registration": "9H-WDI",
      "aircraftType": "A21N",
      "originCountry": null,
      "lat": 35.2397,
      "lon": 32.3075,
      "altitudeFeet": 22575,
      "speedKnots": 423,
      "heading": 108,
      "verticalRateMps": -1824,
      "onGround": false,
      "squawk": "5457",
      "lastContactAgeSec": 0,
      "timePositionAgeSec": 0
    },
    {
      "id": "4bab24",
      "callsign": "THY5ER",
      "registration": "TC-JYD",
      "aircraftType": "B739",
      "originCountry": null,
      "lat": 36.9727,
      "lon": 32.3409,
      "altitudeFeet": 37400,
      "speedKnots": 479,
      "heading": 128,
      "verticalRateMps": 0,
      "onGround": false,
      "squawk": "5055",
      "lastContactAgeSec": 0,
      "timePositionAgeSec": 0
    },
    {
      "id": "503fc5",
      "callsign": "ELY5140",
      "registration": "LY-OEX",
      "aircraftType": "B738",
      "originCountry": null,
      "lat": 34.6708,
      "lon": 32.4294,
      "altitudeFeet": 3425,
      "speedKnots": 203,
      "heading": 190,
      "verticalRateMps": 1408,
      "onGround": false,
      "squawk": "4150",
      "lastContactAgeSec": 0,
      "timePositionAgeSec": 1
    },
    {
      "id": "5001e3",
      "callsign": "MEA241",
      "registration": "T7-ME7",
      "aircraftType": "A21N",
      "originCountry": null,
      "lat": 34.4619,
      "lon": 32.6129,
      "altitudeFeet": 29750,
      "speedKnots": 459,
      "heading": 284,
      "verticalRateMps": 672,
      "onGround": false,
      "squawk": "5605",
      "lastContactAgeSec": 0,
      "timePositionAgeSec": 0
    },
    {
      "id": "4ba9e8",
      "callsign": "THY47G",
      "registration": "TC-JOH",
      "aircraftType": "A333",
      "originCountry": null,
      "lat": 30.8519,
      "lon": 32.7578,
      "altitudeFeet": 40800,
      "speedKnots": 465,
      "heading": 314,
      "verticalRateMps": 0,
      "onGround": false,
      "squawk": "4071",
      "lastContactAgeSec": 0,
      "timePositionAgeSec": 0
    },
    {
      "id": "4a3121",
      "callsign": "AIZ441",
      "registration": "YR-LIA",
      "aircraftType": "A320",
      "originCountry": null,
      "lat": 32.8968,
      "lon": 32.8247,
      "altitudeFeet": 29650,
      "speedKnots": 454,
      "heading": 319,
      "verticalRateMps": 704,
      "onGround": false,
      "squawk": "2267",
      "lastContactAgeSec": 0,
      "timePositionAgeSec": 0
    },
    {
      "id": "4d22b5",
      "callsign": "RYR708",
      "registration": "9H-LON",
      "aircraftType": "A320",
      "originCountry": null,
      "lat": 35.0643,
      "lon": 32.8881,
      "altitudeFeet": 17025,
      "speedKnots": 394,
      "heading": 107,
      "verticalRateMps": -2048,
      "onGround": false,
      "squawk": "7101",
      "lastContactAgeSec": 0,
      "timePositionAgeSec": 0
    },
    {
      "id": "151e07",
      "callsign": "SDM5956",
      "registration": "RA-73223",
      "aircraftType": "B738",
      "originCountry": null,
      "lat": 36.795,
      "lon": 33.0403,
      "altitudeFeet": 37425,
      "speedKnots": 507,
      "heading": 70,
      "verticalRateMps": 64,
      "onGround": false,
      "squawk": "6141",
      "lastContactAgeSec": 0,
      "timePositionAgeSec": 1
    },
    {
      "id": "491d81",
      "callsign": "NJE921R",
      "registration": "CS-GLA",
      "aircraftType": "GLEX",
      "originCountry": null,
      "lat": 34.7177,
      "lon": 33.2364,
      "altitudeFeet": 15275,
      "speedKnots": 319,
      "heading": 270,
      "verticalRateMps": 1792,
      "onGround": false,
      "squawk": "7351",
      "lastContactAgeSec": 0,
      "timePositionAgeSec": 0
    },
    {
      "id": "60084f",
      "callsign": "AHY055",
      "registration": "4K-AZ79",
      "aircraftType": "A320",
      "originCountry": null,
      "lat": 32.8332,
      "lon": 33.2474,
      "altitudeFeet": 37500,
      "speedKnots": 431,
      "heading": 192,
      "verticalRateMps": 0,
      "onGround": false,
      "squawk": "1165",
      "lastContactAgeSec": 0,
      "timePositionAgeSec": 0
    },
    {
      "id": "4d252b",
      "callsign": "WZZ64",
      "registration": "9H-WNE",
      "aircraftType": "A21N",
      "originCountry": null,
      "lat": 33.2307,
      "lon": 33.2954,
      "altitudeFeet": 33025,
      "speedKnots": 474,
      "heading": 139,
      "verticalRateMps": -4352,
      "onGround": false,
      "squawk": "5550",
      "lastContactAgeSec": 0,
      "timePositionAgeSec": 0
    },
    {
      "id": "738069",
      "callsign": "ELY285",
      "registration": "4X-EKO",
      "aircraftType": "B738",
      "originCountry": null,
      "lat": 32.5408,
      "lon": 33.3318,
      "altitudeFeet": 29850,
      "speedKnots": 433,
      "heading": 308,
      "verticalRateMps": 1248,
      "onGround": false,
      "squawk": "2243",
      "lastContactAgeSec": 0,
      "timePositionAgeSec": 0
    },
    {
      "id": "504e65",
      "callsign": "FIE7491",
      "registration": "ER-00007",
      "aircraftType": "A320",
      "originCountry": null,
      "lat": 33.8334,
      "lon": 33.4284,
      "altitudeFeet": 37525,
      "speedKnots": 430,
      "heading": 193,
      "verticalRateMps": 0,
      "onGround": false,
      "squawk": "5353",
      "lastContactAgeSec": 0,
      "timePositionAgeSec": 1
    },
    {
      "id": "4d200c",
      "callsign": "WZZ44LB",
      "registration": "9H-WNL",
      "aircraftType": "A21N",
      "originCountry": null,
      "lat": 32.4328,
      "lon": 33.6408,
      "altitudeFeet": 26700,
      "speedKnots": 399,
      "heading": 310,
      "verticalRateMps": 1504,
      "onGround": false,
      "squawk": "1361",
      "lastContactAgeSec": 0,
      "timePositionAgeSec": 0
    },
    {
      "id": "739474",
      "callsign": "LHK06",
      "registration": "4X-BEP",
      "aircraftType": "S76",
      "originCountry": null,
      "lat": 34.8018,
      "lon": 33.6471,
      "altitudeFeet": 1225,
      "speedKnots": 155,
      "heading": 342,
      "verticalRateMps": 0,
      "onGround": false,
      "squawk": "7577",
      "lastContactAgeSec": 0,
      "timePositionAgeSec": 0
    },
    {
      "id": "4a482d",
      "callsign": "ISR883",
      "registration": "YR-RAM",
      "aircraftType": "A320",
      "originCountry": null,
      "lat": 33.5102,
      "lon": 34.1193,
      "altitudeFeet": 28575,
      "speedKnots": 452,
      "heading": 354,
      "verticalRateMps": 864,
      "onGround": false,
      "squawk": "2272",
      "lastContactAgeSec": 0,
      "timePositionAgeSec": 0
    },
    {
      "id": "507cba",
      "callsign": "MFX374",
      "registration": "UK32076",
      "aircraftType": "A320",
      "originCountry": null,
      "lat": 32.603,
      "lon": 34.2237,
      "altitudeFeet": 19100,
      "speedKnots": 382,
      "heading": 354,
      "verticalRateMps": 1088,
      "onGround": false,
      "squawk": "1157",
      "lastContactAgeSec": 0,
      "timePositionAgeSec": 0
    },
    {
      "id": "5001d4",
      "callsign": "MEA251",
      "registration": "T7-ME2",
      "aircraftType": "A21N",
      "originCountry": null,
      "lat": 34.2924,
      "lon": 34.2723,
      "altitudeFeet": 22500,
      "speedKnots": 420,
      "heading": 295,
      "verticalRateMps": 896,
      "onGround": false,
      "squawk": "5606",
      "lastContactAgeSec": 0,
      "timePositionAgeSec": 1
    },
    {
      "id": "7406e4",
      "callsign": "AWS401",
      "registration": "JY-AWD",
      "aircraftType": "H25B",
      "originCountry": null,
      "lat": 35.4155,
      "lon": 34.5253,
      "altitudeFeet": 35475,
      "speedKnots": 482,
      "heading": 139,
      "verticalRateMps": 192,
      "onGround": false,
      "squawk": "2004",
      "lastContactAgeSec": 0,
      "timePositionAgeSec": 0
    },
    {
      "id": "4d203b",
      "callsign": "U8103",
      "registration": "9H-ISM",
      "aircraftType": "B738",
      "originCountry": null,
      "lat": 32.0364,
      "lon": 34.5582,
      "altitudeFeet": 8025,
      "speedKnots": 281,
      "heading": 303,
      "verticalRateMps": 928,
      "onGround": false,
      "squawk": "4140",
      "lastContactAgeSec": 0,
      "timePositionAgeSec": 0
    },
    {
      "id": "4521bf",
      "callsign": "CYF153",
      "registration": null,
      "aircraftType": null,
      "originCountry": null,
      "lat": 32.3201,
      "lon": 34.6194,
      "altitudeFeet": 6725,
      "speedKnots": 295,
      "heading": 113,
      "verticalRateMps": -864,
      "onGround": false,
      "squawk": "2261",
      "lastContactAgeSec": 0,
      "timePositionAgeSec": 0
    },
    {
      "id": "3c7865",
      "callsign": "VJH713",
      "registration": "D-ANCE",
      "aircraftType": "E35L",
      "originCountry": null,
      "lat": 32.0062,
      "lon": 34.7041,
      "altitudeFeet": 6050,
      "speedKnots": 274,
      "heading": 289,
      "verticalRateMps": 2432,
      "onGround": false,
      "squawk": "5542",
      "lastContactAgeSec": 0,
      "timePositionAgeSec": 0
    },
    {
      "id": "4d2067",
      "callsign": "WMT7705",
      "registration": "9H-WNY",
      "aircraftType": "A21N",
      "originCountry": null,
      "lat": 32.2447,
      "lon": 34.8381,
      "altitudeFeet": 5000,
      "speedKnots": 248,
      "heading": 107,
      "verticalRateMps": -1184,
      "onGround": false,
      "squawk": "4303",
      "lastContactAgeSec": 0,
      "timePositionAgeSec": 0
    },
    {
      "id": "45205e",
      "callsign": "BBG692",
      "registration": "LZ-MVK",
      "aircraftType": "B733",
      "originCountry": null,
      "lat": 31.857,
      "lon": 34.9467,
      "altitudeFeet": 20075,
      "speedKnots": 3,
      "heading": 185,
      "verticalRateMps": 1280,
      "onGround": false,
      "squawk": "4143",
      "lastContactAgeSec": 0,
      "timePositionAgeSec": 28
    },
    {
      "id": "500141",
      "callsign": "T7MIK",
      "registration": "T7-MIK",
      "aircraftType": "FA8X",
      "originCountry": null,
      "lat": 33.7974,
      "lon": 35.4108,
      "altitudeFeet": 3900,
      "speedKnots": 256,
      "heading": 313,
      "verticalRateMps": 2336,
      "onGround": false,
      "squawk": "5610",
      "lastContactAgeSec": 0,
      "timePositionAgeSec": 0
    },
    {
      "id": "73940f",
      "callsign": "4XCBD",
      "registration": "4X-CBD",
      "aircraftType": "PA31",
      "originCountry": null,
      "lat": 32.1065,
      "lon": 35.4954,
      "altitudeFeet": 11750,
      "speedKnots": 162,
      "heading": 205,
      "verticalRateMps": 0,
      "onGround": false,
      "squawk": "5202",
      "lastContactAgeSec": 0,
      "timePositionAgeSec": 0
    },
    {
      "id": "74482a",
      "callsign": "RJA502",
      "registration": "JY-RAJ",
      "aircraftType": "A20N",
      "originCountry": null,
      "lat": 31.054,
      "lon": 35.9918,
      "altitudeFeet": 23125,
      "speedKnots": 409,
      "heading": 31,
      "verticalRateMps": -2688,
      "onGround": false,
      "squawk": "6162",
      "lastContactAgeSec": 0,
      "timePositionAgeSec": 0
    },
    {
      "id": "748016",
      "callsign": "MEA311",
      "registration": "OD-MRT",
      "aircraftType": "A320",
      "originCountry": null,
      "lat": 31.9018,
      "lon": 36.008,
      "altitudeFeet": 9550,
      "speedKnots": 326,
      "heading": 26,
      "verticalRateMps": 2592,
      "onGround": false,
      "squawk": "0714",
      "lastContactAgeSec": 0,
      "timePositionAgeSec": 0
    },
    {
      "id": "4a2aac",
      "callsign": "DNA542",
      "registration": "YR-JUL",
      "aircraftType": "A320",
      "originCountry": null,
      "lat": 34.2202,
      "lon": 36.577,
      "altitudeFeet": 24225,
      "speedKnots": 363,
      "heading": 7,
      "verticalRateMps": 1504,
      "onGround": false,
      "squawk": "5742",
      "lastContactAgeSec": 0,
      "timePositionAgeSec": 1
    },
    {
      "id": "711469",
      "callsign": "KNE2986",
      "registration": "HZ-NS95",
      "aircraftType": "A20N",
      "originCountry": null,
      "lat": 34.6648,
      "lon": 36.9215,
      "altitudeFeet": 39675,
      "speedKnots": 472,
      "heading": 149,
      "verticalRateMps": 0,
      "onGround": false,
      "squawk": "5035",
      "lastContactAgeSec": 0,
      "timePositionAgeSec": 0
    },
    {
      "id": "744822",
      "callsign": "RJA827",
      "registration": "JY-RAB",
      "aircraftType": "A20N",
      "originCountry": null,
      "lat": 32.3261,
      "lon": 37.041,
      "altitudeFeet": 27000,
      "speedKnots": 405,
      "heading": 232,
      "verticalRateMps": -3712,
      "onGround": false,
      "squawk": "7262",
      "lastContactAgeSec": 0,
      "timePositionAgeSec": 0
    },
    {
      "id": "70606e",
      "callsign": "KAC141",
      "registration": "9K-AKS",
      "aircraftType": "A20N",
      "originCountry": null,
      "lat": 34.3211,
      "lon": 37.1863,
      "altitudeFeet": 38650,
      "speedKnots": 426,
      "heading": 306,
      "verticalRateMps": -32,
      "onGround": false,
      "squawk": "1442",
      "lastContactAgeSec": 0,
      "timePositionAgeSec": 0
    },
    {
      "id": "8963f7",
      "callsign": "UAE1",
      "registration": "A6-EOZ",
      "aircraftType": "A388",
      "originCountry": null,
      "lat": 34.287,
      "lon": 37.243,
      "altitudeFeet": 40750,
      "speedKnots": 461,
      "heading": 306,
      "verticalRateMps": 0,
      "onGround": false,
      "squawk": "0564",
      "lastContactAgeSec": 0,
      "timePositionAgeSec": 0
    },
    {
      "id": "706210",
      "callsign": "JZR327",
      "registration": "9K-CAQ",
      "aircraftType": "A20N",
      "originCountry": null,
      "lat": 34.5217,
      "lon": 37.6434,
      "altitudeFeet": 34375,
      "speedKnots": 457,
      "heading": 340,
      "verticalRateMps": 0,
      "onGround": false,
      "squawk": "1446",
      "lastContactAgeSec": 0,
      "timePositionAgeSec": 0
    },
    {
      "id": "706070",
      "callsign": "KAC155",
      "registration": "9K-APJ",
      "aircraftType": "A339",
      "originCountry": null,
      "lat": 34.1482,
      "lon": 37.8029,
      "altitudeFeet": 36475,
      "speedKnots": 478,
      "heading": 340,
      "verticalRateMps": 0,
      "onGround": false,
      "squawk": "1436",
      "lastContactAgeSec": 0,
      "timePositionAgeSec": 0
    },
    {
      "id": "06a097",
      "callsign": "QTR35E",
      "registration": "A7-AHP",
      "aircraftType": "A320",
      "originCountry": null,
      "lat": 33.6477,
      "lon": 38.0575,
      "altitudeFeet": 34425,
      "speedKnots": 453,
      "heading": 333,
      "verticalRateMps": 0,
      "onGround": false,
      "squawk": "2170",
      "lastContactAgeSec": 0,
      "timePositionAgeSec": 0
    },
    {
      "id": "4baa09",
      "callsign": "THY5102",
      "registration": "TC-JPI",
      "aircraftType": "A320",
      "originCountry": null,
      "lat": 32.8142,
      "lon": 38.0793,
      "altitudeFeet": 37675,
      "speedKnots": 479,
      "heading": 153,
      "verticalRateMps": 0,
      "onGround": false,
      "squawk": "5102",
      "lastContactAgeSec": 0,
      "timePositionAgeSec": 0
    },
    {
      "id": "70612d",
      "callsign": "JZR85",
      "registration": "9K-CBG",
      "aircraftType": "A20N",
      "originCountry": null,
      "lat": 33.4078,
      "lon": 38.2045,
      "altitudeFeet": 32325,
      "speedKnots": 454,
      "heading": 333,
      "verticalRateMps": -32,
      "onGround": false,
      "squawk": "1404",
      "lastContactAgeSec": 0,
      "timePositionAgeSec": 0
    },
    {
      "id": "896727",
      "callsign": "ABY363",
      "registration": "A6-AOA",
      "aircraftType": "A320",
      "originCountry": null,
      "lat": 32.9177,
      "lon": 38.5006,
      "altitudeFeet": 31875,
      "speedKnots": 455,
      "heading": 332,
      "verticalRateMps": -928,
      "onGround": false,
      "squawk": "3431",
      "lastContactAgeSec": 0,
      "timePositionAgeSec": 0
    },
    {
      "id": "748020",
      "callsign": "MEA364",
      "registration": "OD-MRR",
      "aircraftType": "A320",
      "originCountry": null,
      "lat": 31.1157,
      "lon": 38.7588,
      "altitudeFeet": 37725,
      "speedKnots": 464,
      "heading": 178,
      "verticalRateMps": 0,
      "onGround": false,
      "squawk": "2564",
      "lastContactAgeSec": 0,
      "timePositionAgeSec": 1
    },
    {
      "id": "89645b",
      "callsign": "UAE39",
      "registration": "A6-EUF",
      "aircraftType": "A388",
      "originCountry": null,
      "lat": 32.3571,
      "lon": 38.8351,
      "altitudeFeet": 42900,
      "speedKnots": 477,
      "heading": 333,
      "verticalRateMps": 0,
      "onGround": false,
      "squawk": "0551",
      "lastContactAgeSec": 0,
      "timePositionAgeSec": 1
    },
    {
      "id": "8940d6",
      "callsign": "GFA048",
      "registration": "A9C-TH",
      "aircraftType": "A20N",
      "originCountry": null,
      "lat": 31.0353,
      "lon": 39.2315,
      "altitudeFeet": 39875,
      "speedKnots": 473,
      "heading": 129,
      "verticalRateMps": 32,
      "onGround": false,
      "squawk": "5506",
      "lastContactAgeSec": 0,
      "timePositionAgeSec": 0
    },
    {
      "id": "896741",
      "callsign": "ABY793",
      "registration": null,
      "aircraftType": null,
      "originCountry": null,
      "lat": 31.7659,
      "lon": 39.2474,
      "altitudeFeet": 38700,
      "speedKnots": 452,
      "heading": 302,
      "verticalRateMps": 32,
      "onGround": false,
      "squawk": "1716",
      "lastContactAgeSec": 0,
      "timePositionAgeSec": 0
    },
    {
      "id": "0101b2",
      "callsign": "0101B2",
      "registration": "SU-BQL",
      "aircraftType": "A321",
      "originCountry": null,
      "lat": 27.0071,
      "lon": 49.2729,
      "altitudeFeet": 34400,
      "speedKnots": 466,
      "heading": 285,
      "verticalRateMps": 0,
      "onGround": false,
      "squawk": "3435",
      "lastContactAgeSec": 0,
      "timePositionAgeSec": 0
    },
    {
      "id": "06a2f5",
      "callsign": "QTR37K",
      "registration": "A7-BHR",
      "aircraftType": "B789",
      "originCountry": null,
      "lat": 26.5131,
      "lon": 49.7179,
      "altitudeFeet": 34050,
      "speedKnots": 509,
      "heading": 286,
      "verticalRateMps": 960,
      "onGround": false,
      "squawk": "3221",
      "lastContactAgeSec": 0,
      "timePositionAgeSec": 4
    },
    {
      "id": "89642a",
      "callsign": "ETD596",
      "registration": "A6-AEE",
      "aircraftType": "A321",
      "originCountry": null,
      "lat": 26.4325,
      "lon": 49.8583,
      "altitudeFeet": 37525,
      "speedKnots": 471,
      "heading": 107,
      "verticalRateMps": -32,
      "onGround": false,
      "squawk": "0745",
      "lastContactAgeSec": 0,
      "timePositionAgeSec": 0
    }
  ],
  "status": "adsb.lol ok (56)"
}
