{
  "generatedAt": "2026-04-30T21:16:57.960Z",
  "flights": [
    {
      "id": "407a06",
      "callsign": "EZY52DQ",
      "originCountry": "United Kingdom",
      "lat": 41.8378,
      "lon": 27.4889,
      "altitudeFeet": 38150,
      "speedKnots": 421,
      "heading": 318,
      "verticalRateMps": -0.3,
      "onGround": false,
      "squawk": "3222",
      "lastContactAgeSec": 1,
      "timePositionAgeSec": 1
    },
    {
      "id": "4bc8c1",
      "callsign": "PGT1456",
      "originCountry": "Turkey",
      "lat": 37.7471,
      "lon": 27.2886,
      "altitudeFeet": 23875,
      "speedKnots": 392,
      "heading": 339,
      "verticalRateMps": 12,
      "onGround": false,
      "squawk": null,
      "lastContactAgeSec": 1,
      "timePositionAgeSec": 2
    },
    {
      "id": "471efc",
      "callsign": "WZZ37GC",
      "originCountry": "Hungary",
      "lat": 36.4231,
      "lon": 32.1365,
      "altitudeFeet": 37225,
      "speedKnots": 455,
      "heading": 154,
      "verticalRateMps": -5.2,
      "onGround": false,
      "squawk": null,
      "lastContactAgeSec": 1,
      "timePositionAgeSec": 1
    },
    {
      "id": "4bc8ca",
      "callsign": "PGT2138",
      "originCountry": "Turkey",
      "lat": 39.4888,
      "lon": 29.9479,
      "altitudeFeet": 32500,
      "speedKnots": 460,
      "heading": 156,
      "verticalRateMps": 6.2,
      "onGround": false,
      "squawk": null,
      "lastContactAgeSec": 1,
      "timePositionAgeSec": 1
    },
    {
      "id": "742838",
      "callsign": "JAV273",
      "originCountry": "Jordan",
      "lat": 35.1351,
      "lon": 34.0418,
      "altitudeFeet": 32650,
      "speedKnots": 431,
      "heading": 359,
      "verticalRateMps": 0,
      "onGround": false,
      "squawk": "5612",
      "lastContactAgeSec": 1,
      "timePositionAgeSec": 1
    },
    {
      "id": "5003e8",
      "callsign": "T7VRS",
      "originCountry": "San Marino",
      "lat": 35.3192,
      "lon": 26.9244,
      "altitudeFeet": 38775,
      "speedKnots": 410,
      "heading": 323,
      "verticalRateMps": -0.3,
      "onGround": false,
      "squawk": "1437",
      "lastContactAgeSec": 1,
      "timePositionAgeSec": 1
    },
    {
      "id": "873312",
      "callsign": "ANA216",
      "originCountry": "Japan",
      "lat": 41.4008,
      "lon": 43.9482,
      "altitudeFeet": 35425,
      "speedKnots": 522,
      "heading": 92,
      "verticalRateMps": -0.3,
      "onGround": false,
      "squawk": "7552",
      "lastContactAgeSec": 1,
      "timePositionAgeSec": 1
    },
    {
      "id": "739347",
      "callsign": "4XCNZ",
      "originCountry": "Israel",
      "lat": 35.5619,
      "lon": 31.2655,
      "altitudeFeet": 37775,
      "speedKnots": 459,
      "heading": 145,
      "verticalRateMps": 0,
      "onGround": false,
      "squawk": "1151",
      "lastContactAgeSec": 1,
      "timePositionAgeSec": 1
    },
    {
      "id": "4bc88a",
      "callsign": "PGT240",
      "originCountry": "Turkey",
      "lat": 41.1169,
      "lon": 46.0101,
      "altitudeFeet": 35425,
      "speedKnots": 492,
      "heading": 109,
      "verticalRateMps": 0,
      "onGround": false,
      "squawk": "5123",
      "lastContactAgeSec": 1,
      "timePositionAgeSec": 1
    },
    {
      "id": "4bc890",
      "callsign": "PGT318",
      "originCountry": "Turkey",
      "lat": 41.4266,
      "lon": 44.6454,
      "altitudeFeet": 17375,
      "speedKnots": 374,
      "heading": 353,
      "verticalRateMps": -13.7,
      "onGround": false,
      "squawk": "5144",
      "lastContactAgeSec": 1,
      "timePositionAgeSec": 1
    },
    {
      "id": "738064",
      "callsign": "ELY364",
      "originCountry": "Israel",
      "lat": 40.4316,
      "lon": 25.9856,
      "altitudeFeet": 37300,
      "speedKnots": 481,
      "heading": 131,
      "verticalRateMps": 0,
      "onGround": false,
      "squawk": "7104",
      "lastContactAgeSec": 1,
      "timePositionAgeSec": 2
    },
    {
      "id": "738052",
      "callsign": "ELY352",
      "originCountry": "Israel",
      "lat": 33.5928,
      "lon": 32.4917,
      "altitudeFeet": 33825,
      "speedKnots": 508,
      "heading": 129,
      "verticalRateMps": 0,
      "onGround": false,
      "squawk": "5564",
      "lastContactAgeSec": 1,
      "timePositionAgeSec": 1
    },
    {
      "id": "73934e",
      "callsign": "HEZ352",
      "originCountry": "Israel",
      "lat": 32.6909,
      "lon": 34.0172,
      "altitudeFeet": 16300,
      "speedKnots": 380,
      "heading": 141,
      "verticalRateMps": -7.5,
      "onGround": false,
      "squawk": "4130",
      "lastContactAgeSec": 1,
      "timePositionAgeSec": 2
    },
    {
      "id": "841c48",
      "callsign": "JAL44",
      "originCountry": "Japan",
      "lat": 42.7249,
      "lon": 27.5924,
      "altitudeFeet": 34950,
      "speedKnots": 536,
      "heading": 126,
      "verticalRateMps": 0,
      "onGround": false,
      "squawk": "4622",
      "lastContactAgeSec": 1,
      "timePositionAgeSec": 2
    },
    {
      "id": "45213d",
      "callsign": "MSC2966",
      "originCountry": "Bulgaria",
      "lat": 39.1729,
      "lon": 25.3602,
      "altitudeFeet": 34475,
      "speedKnots": 424,
      "heading": 327,
      "verticalRateMps": 0,
      "onGround": false,
      "squawk": "7366",
      "lastContactAgeSec": 1,
      "timePositionAgeSec": 1
    },
    {
      "id": "738284",
      "callsign": "ISR116",
      "originCountry": "Israel",
      "lat": 32.1125,
      "lon": 34.6772,
      "altitudeFeet": 3675,
      "speedKnots": 175,
      "heading": 121,
      "verticalRateMps": -4.9,
      "onGround": false,
      "squawk": "3452",
      "lastContactAgeSec": 1,
      "timePositionAgeSec": 2
    },
    {
      "id": "738289",
      "callsign": "ISR892",
      "originCountry": "Israel",
      "lat": 41.3462,
      "lon": 40.8303,
      "altitudeFeet": 36475,
      "speedKnots": 396,
      "heading": 246,
      "verticalRateMps": 0,
      "onGround": false,
      "squawk": "6750",
      "lastContactAgeSec": 1,
      "timePositionAgeSec": 1
    },
    {
      "id": "896401",
      "callsign": "ABY418",
      "originCountry": "United Arab Emirates",
      "lat": 25.4303,
      "lon": 55.7811,
      "altitudeFeet": 13575,
      "speedKnots": 389,
      "heading": 100,
      "verticalRateMps": 11.4,
      "onGround": false,
      "squawk": "3455",
      "lastContactAgeSec": 1,
      "timePositionAgeSec": 8
    },
    {
      "id": "846098",
      "callsign": "JAL46",
      "originCountry": "Japan",
      "lat": 42.062,
      "lon": 28.7947,
      "altitudeFeet": 35075,
      "speedKnots": 548,
      "heading": 116,
      "verticalRateMps": 0,
      "onGround": false,
      "squawk": "7560",
      "lastContactAgeSec": 1,
      "timePositionAgeSec": 2
    },
    {
      "id": "896314",
      "callsign": "UAE110",
      "originCountry": "United Arab Emirates",
      "lat": 25.2238,
      "lon": 55.4167,
      "altitudeFeet": 525,
      "speedKnots": 146,
      "heading": 301,
      "verticalRateMps": -3.9,
      "onGround": false,
      "squawk": "1616",
      "lastContactAgeSec": 1,
      "timePositionAgeSec": 1
    },
    {
      "id": "8963d2",
      "callsign": "UAE815",
      "originCountry": "United Arab Emirates",
      "lat": 24.9321,
      "lon": 55.6563,
      "altitudeFeet": 19300,
      "speedKnots": 439,
      "heading": 121,
      "verticalRateMps": 15.3,
      "onGround": false,
      "squawk": "6221",
      "lastContactAgeSec": 1,
      "timePositionAgeSec": 1
    },
    {
      "id": "4bb14c",
      "callsign": "THY6251",
      "originCountry": "Turkey",
      "lat": 40.8855,
      "lon": 42.83,
      "altitudeFeet": 34475,
      "speedKnots": 434,
      "heading": 274,
      "verticalRateMps": 0.3,
      "onGround": false,
      "squawk": "2641",
      "lastContactAgeSec": 1,
      "timePositionAgeSec": 1
    },
    {
      "id": "744de2",
      "callsign": "FJR301",
      "originCountry": "Jordan",
      "lat": 32.2084,
      "lon": 34.5192,
      "altitudeFeet": 16675,
      "speedKnots": 368,
      "heading": 134,
      "verticalRateMps": -9.7,
      "onGround": false,
      "squawk": "5312",
      "lastContactAgeSec": 1,
      "timePositionAgeSec": 1
    },
    {
      "id": "4064bb",
      "callsign": "EXS16M",
      "originCountry": "United Kingdom",
      "lat": 37.797,
      "lon": 26.3138,
      "altitudeFeet": 39150,
      "speedKnots": 432,
      "heading": 329,
      "verticalRateMps": 2.3,
      "onGround": false,
      "squawk": "6453",
      "lastContactAgeSec": 1,
      "timePositionAgeSec": 1
    },
    {
      "id": "896644",
      "callsign": "FDB574",
      "originCountry": "United Arab Emirates",
      "lat": 24.8243,
      "lon": 56.4183,
      "altitudeFeet": 17850,
      "speedKnots": 323,
      "heading": 295,
      "verticalRateMps": -6.5,
      "onGround": false,
      "squawk": null,
      "lastContactAgeSec": 1,
      "timePositionAgeSec": 1
    },
    {
      "id": "89660c",
      "callsign": "FDB524",
      "originCountry": "United Arab Emirates",
      "lat": 25.1509,
      "lon": 55.5477,
      "altitudeFeet": 3100,
      "speedKnots": 201,
      "heading": 302,
      "verticalRateMps": -4.9,
      "onGround": false,
      "squawk": "4023",
      "lastContactAgeSec": 1,
      "timePositionAgeSec": 1
    },
    {
      "id": "8964c6",
      "callsign": "ABY842",
      "originCountry": "United Arab Emirates",
      "lat": 29.4112,
      "lon": 33.3592,
      "altitudeFeet": 32850,
      "speedKnots": 344,
      "heading": 288,
      "verticalRateMps": -4.9,
      "onGround": false,
      "squawk": "3406",
      "lastContactAgeSec": 1,
      "timePositionAgeSec": 2
    },
    {
      "id": "40796a",
      "callsign": "TOM719",
      "originCountry": "United Kingdom",
      "lat": 30.0154,
      "lon": 31.7199,
      "altitudeFeet": 37275,
      "speedKnots": 396,
      "heading": 308,
      "verticalRateMps": 0,
      "onGround": false,
      "squawk": "6126",
      "lastContactAgeSec": 1,
      "timePositionAgeSec": 1
    },
    {
      "id": "700011",
      "callsign": "KMF9919",
      "originCountry": "Afghanistan",
      "lat": 40.7238,
      "lon": 46.9786,
      "altitudeFeet": 36375,
      "speedKnots": 422,
      "heading": 273,
      "verticalRateMps": 0,
      "onGround": false,
      "squawk": "1720",
      "lastContactAgeSec": 1,
      "timePositionAgeSec": 1
    },
    {
      "id": "70620c",
      "callsign": "JZR3724",
      "originCountry": "Kuwait",
      "lat": 28.6695,
      "lon": 32.5448,
      "altitudeFeet": 38475,
      "speedKnots": 504,
      "heading": 142,
      "verticalRateMps": 0.3,
      "onGround": false,
      "squawk": "7313",
      "lastContactAgeSec": 1,
      "timePositionAgeSec": 6
    },
    {
      "id": "406f7c",
      "callsign": "BAW61",
      "originCountry": "United Kingdom",
      "lat": 34.2812,
      "lon": 30.006,
      "altitudeFeet": 38775,
      "speedKnots": 526,
      "heading": 133,
      "verticalRateMps": 0,
      "onGround": false,
      "squawk": "1176",
      "lastContactAgeSec": 1,
      "timePositionAgeSec": 1
    },
    {
      "id": "50840a",
      "callsign": "UTN9122",
      "originCountry": "Ukraine",
      "lat": 34.0367,
      "lon": 30.9112,
      "altitudeFeet": 36825,
      "speedKnots": 414,
      "heading": 358,
      "verticalRateMps": 0,
      "onGround": false,
      "squawk": "7316",
      "lastContactAgeSec": 1,
      "timePositionAgeSec": 1
    },
    {
      "id": "06a2e3",
      "callsign": "QTR25Q",
      "originCountry": "Qatar",
      "lat": 25.7948,
      "lon": 49.2187,
      "altitudeFeet": 32075,
      "speedKnots": 544,
      "heading": 105,
      "verticalRateMps": -4.5,
      "onGround": false,
      "squawk": "0162",
      "lastContactAgeSec": 1,
      "timePositionAgeSec": 4
    },
    {
      "id": "06a2f8",
      "callsign": "QTR60F",
      "originCountry": "Qatar",
      "lat": 25.1735,
      "lon": 51.7616,
      "altitudeFeet": 4950,
      "speedKnots": 206,
      "heading": 158,
      "verticalRateMps": 2,
      "onGround": false,
      "squawk": "5200",
      "lastContactAgeSec": 1,
      "timePositionAgeSec": 70
    },
    {
      "id": "49d414",
      "callsign": "TVP7111",
      "originCountry": "Czech Republic",
      "lat": 35.5463,
      "lon": 27.3471,
      "altitudeFeet": 36650,
      "speedKnots": 407,
      "heading": 335,
      "verticalRateMps": 0,
      "onGround": false,
      "squawk": null,
      "lastContactAgeSec": 1,
      "timePositionAgeSec": 1
    },
    {
      "id": "3c7087",
      "callsign": "HRN611",
      "originCountry": "Germany",
      "lat": 31.8164,
      "lon": 31.2754,
      "altitudeFeet": 40000,
      "speedKnots": 458,
      "heading": 204,
      "verticalRateMps": 0,
      "onGround": false,
      "squawk": "1627",
      "lastContactAgeSec": 1,
      "timePositionAgeSec": 1
    },
    {
      "id": "46bc4b",
      "callsign": "AEE8KS",
      "originCountry": "Greece",
      "lat": 36.9559,
      "lon": 26.524,
      "altitudeFeet": 13725,
      "speedKnots": 298,
      "heading": 96,
      "verticalRateMps": -12.7,
      "onGround": false,
      "squawk": "1416",
      "lastContactAgeSec": 1,
      "timePositionAgeSec": 1
    },
    {
      "id": "155c6c",
      "callsign": "RWZ4639",
      "originCountry": "Russian Federation",
      "lat": 41.356,
      "lon": 42.4514,
      "altitudeFeet": 34475,
      "speedKnots": 391,
      "heading": 260,
      "verticalRateMps": 0,
      "onGround": false,
      "squawk": "4162",
      "lastContactAgeSec": 1,
      "timePositionAgeSec": 2
    },
    {
      "id": "48e95e",
      "callsign": "LOT6860",
      "originCountry": "Poland",
      "lat": 41.0272,
      "lon": 29.6209,
      "altitudeFeet": 40275,
      "speedKnots": 117,
      "heading": 195,
      "verticalRateMps": 0,
      "onGround": false,
      "squawk": "2365",
      "lastContactAgeSec": 1,
      "timePositionAgeSec": 1859
    },
    {
      "id": "46dca2",
      "callsign": "SEH721",
      "originCountry": "Greece",
      "lat": 32.0324,
      "lon": 34.5285,
      "altitudeFeet": 14100,
      "speedKnots": 320,
      "heading": 274,
      "verticalRateMps": 20.8,
      "onGround": false,
      "squawk": "4151",
      "lastContactAgeSec": 1,
      "timePositionAgeSec": 1
    },
    {
      "id": "503d74",
      "callsign": "AHY078",
      "originCountry": "Lithuania",
      "lat": 40.7922,
      "lon": 37.3191,
      "altitudeFeet": 31525,
      "speedKnots": 501,
      "heading": 80,
      "verticalRateMps": 0,
      "onGround": false,
      "squawk": "5156",
      "lastContactAgeSec": 1,
      "timePositionAgeSec": 1
    },
    {
      "id": "4b9e55",
      "callsign": "MSC781",
      "originCountry": "Turkey",
      "lat": 30.4503,
      "lon": 31.5593,
      "altitudeFeet": 37150,
      "speedKnots": 457,
      "heading": 352,
      "verticalRateMps": 0,
      "onGround": false,
      "squawk": "6142",
      "lastContactAgeSec": 1,
      "timePositionAgeSec": 1
    },
    {
      "id": "71c522",
      "callsign": "AAR512",
      "originCountry": "Republic of Korea",
      "lat": 42.9692,
      "lon": 24.5547,
      "altitudeFeet": 36900,
      "speedKnots": 531,
      "heading": 91,
      "verticalRateMps": 0,
      "onGround": false,
      "squawk": "1253",
      "lastContactAgeSec": 1,
      "timePositionAgeSec": 1
    },
    {
      "id": "46b8b3",
      "callsign": "AEE4PR",
      "originCountry": "Greece",
      "lat": 37.2871,
      "lon": 25.2288,
      "altitudeFeet": 5175,
      "speedKnots": 254,
      "heading": 116,
      "verticalRateMps": -9.4,
      "onGround": false,
      "squawk": "6747",
      "lastContactAgeSec": 1,
      "timePositionAgeSec": 1
    },
    {
      "id": "4b187c",
      "callsign": "SWR2646",
      "originCountry": "Switzerland",
      "lat": 40.7901,
      "lon": 45.0347,
      "altitudeFeet": 41450,
      "speedKnots": 489,
      "heading": 93,
      "verticalRateMps": -0.3,
      "onGround": false,
      "squawk": "3042",
      "lastContactAgeSec": 1,
      "timePositionAgeSec": 1
    },
    {
      "id": "408064",
      "callsign": "WUK7PY",
      "originCountry": "United Kingdom",
      "lat": 38.6742,
      "lon": 26.5781,
      "altitudeFeet": 38550,
      "speedKnots": 417,
      "heading": 324,
      "verticalRateMps": 0.3,
      "onGround": false,
      "squawk": "3277",
      "lastContactAgeSec": 1,
      "timePositionAgeSec": 2
    },
    {
      "id": "408228",
      "callsign": "BAW398",
      "originCountry": "United Kingdom",
      "lat": 33.9647,
      "lon": 28.4895,
      "altitudeFeet": 35850,
      "speedKnots": 504,
      "heading": 139,
      "verticalRateMps": 0,
      "onGround": false,
      "squawk": "5235",
      "lastContactAgeSec": 1,
      "timePositionAgeSec": 4
    },
    {
      "id": "4a4eae",
      "callsign": "HYS7412",
      "originCountry": "Romania",
      "lat": 42.0104,
      "lon": 29.2051,
      "altitudeFeet": 36250,
      "speedKnots": 430,
      "heading": 344,
      "verticalRateMps": 0.3,
      "onGround": false,
      "squawk": "7335",
      "lastContactAgeSec": 1,
      "timePositionAgeSec": 249
    },
    {
      "id": "70c105",
      "callsign": "OMA172",
      "originCountry": "Oman",
      "lat": 42.1048,
      "lon": 26.0667,
      "altitudeFeet": 37125,
      "speedKnots": 538,
      "heading": 122,
      "verticalRateMps": -0.3,
      "onGround": false,
      "squawk": "4340",
      "lastContactAgeSec": 1,
      "timePositionAgeSec": 1
    },
    {
      "id": "7609e4",
      "callsign": "ABQ218",
      "originCountry": "Pakistan",
      "lat": 31.7704,
      "lon": 70.087,
      "altitudeFeet": 35525,
      "speedKnots": 392,
      "heading": 228,
      "verticalRateMps": -0.3,
      "onGround": false,
      "squawk": null,
      "lastContactAgeSec": 1,
      "timePositionAgeSec": 2
    },
    {
      "id": "45d06e",
      "callsign": "VKG098",
      "originCountry": "Denmark",
      "lat": 35.4506,
      "lon": 24.3864,
      "altitudeFeet": 4225,
      "speedKnots": 173,
      "heading": 280,
      "verticalRateMps": 1,
      "onGround": false,
      "squawk": "6030",
      "lastContactAgeSec": 1,
      "timePositionAgeSec": 2
    },
    {
      "id": "4a4d79",
      "callsign": "HYM458",
      "originCountry": "Romania",
      "lat": 32.013,
      "lon": 34.8618,
      "altitudeFeet": 350,
      "speedKnots": 179,
      "heading": 260,
      "verticalRateMps": 14.3,
      "onGround": false,
      "squawk": null,
      "lastContactAgeSec": 1,
      "timePositionAgeSec": 1
    },
    {
      "id": "48664a",
      "callsign": "CAI3X",
      "originCountry": "Kingdom of the Netherlands",
      "lat": 42.674,
      "lon": 27.3257,
      "altitudeFeet": 35975,
      "speedKnots": 419,
      "heading": 314,
      "verticalRateMps": 0,
      "onGround": false,
      "squawk": "5327",
      "lastContactAgeSec": 1,
      "timePositionAgeSec": 1
    },
    {
      "id": "4bcdee",
      "callsign": "SXS4HF",
      "originCountry": "Turkey",
      "lat": 38.8284,
      "lon": 29.3104,
      "altitudeFeet": 35175,
      "speedKnots": 390,
      "heading": 245,
      "verticalRateMps": -4.9,
      "onGround": false,
      "squawk": null,
      "lastContactAgeSec": 1,
      "timePositionAgeSec": 1
    },
    {
      "id": "4bcdeb",
      "callsign": "SXS3AN",
      "originCountry": "Turkey",
      "lat": 42.5786,
      "lon": 27.0379,
      "altitudeFeet": 35000,
      "speedKnots": 502,
      "heading": 111,
      "verticalRateMps": -0.3,
      "onGround": false,
      "squawk": "7650",
      "lastContactAgeSec": 1,
      "timePositionAgeSec": 1
    },
    {
      "id": "4bcdd6",
      "callsign": "SXS2LL",
      "originCountry": "Turkey",
      "lat": 37.3516,
      "lon": 29.8131,
      "altitudeFeet": 19575,
      "speedKnots": 387,
      "heading": 116,
      "verticalRateMps": -7.8,
      "onGround": false,
      "squawk": "7642",
      "lastContactAgeSec": 1,
      "timePositionAgeSec": 1
    }
  ],
  "status": "opensky fallback (56)"
}
